{
  "$schema": "https://aka.ms/ASPackageTemplate",
  "contentVersion": "1.0.0.0",
  "package": {
    "name": "Cyolo",
    "version": "1.0.0",
    "publisher": "Cyolo"
  },
  "contentItems": [
    {
      "type": "DataConnector",
      "path": "Solutions/Cyolo/Data Connectors/CyoloDataConnectorDefinition.json",
      "id": "CyoloDataConnectorDefinition"
    },
    {
      "type": "DataConnector",
      "path": "Solutions/Cyolo/Data Connectors/CyoloDataConnector.json",
      "id": "CyoloDataConnector"
    },
    {
      "type": "Workbook",
      "path": "Solutions/Cyolo/Workbooks/CyoloAccessInsights.json",
      "id": "CyoloAccessInsights"
    },
    {
      "type": "AnalyticRule",
      "path": "Solutions/Cyolo/IncidentScenarios/CyoloSuspiciousAccess.json",
      "id": "CyoloSuspiciousAccess"
    },
    {
      "type": "SolutionMetadata",
      "path": "Solutions/Cyolo/Metadata/SolutionMetadata.json",
      "id": "SolutionMetadata"
    }
  ]
}
