{
  "version": "1.0.0",
  "name": "Cyolo",
  "publisher": "Cyolo",
  "author": "Cyolo",
  "description": "Ingests Cyolo access logs into Microsoft Sentinel via REST API Poller.",
  "support": {
    "name": "Cyolo",
    "email": "support@cyolo.io",
    "tier": "Partner"
  },
  "dataConnectors": [
    {
      "id": "CyoloDataConnector",
      "template": "Solutions/Cyolo/Data Connectors/CyoloDataConnector.json"
    }
  ],
  "analyticRules": [
    {
      "id": "CyoloSuspiciousAccess",
      "template": "Solutions/Cyolo/IncidentScenarios/CyoloSuspiciousAccess.json"
    }
  ],
  "workbooks": [
    {
      "id": "CyoloAccessInsights",
      "template": "Solutions/Cyolo/Workbooks/CyoloAccessInsights.json"
    }
  ],
  "baseContentId": "Cyolo.Sentinel"
}